omninumpy/__init__.py
omninumpy/backend.py
omninumpy/core.py
omninumpy/interface.py
omninumpy/version.py
omninumpy/core/__init__.py
omninumpy/core/array_core.py
omninumpy/core/compat_core.py
omninumpy/core/dtype_core.py
omninumpy/core/linalg_core.py
omninumpy/core/math_core.py
omninumpy/core/random_core.py
omninumpy/core/reduce_core.py
omninumpy/core/shape_core.py
omninumpy/tests/test_backends.py
omninumpy/tests/test_basic.py
omninumpy-0.1.65.dist-info/licenses/LICENSE
omninumpy-0.1.65.dist-info/METADATA
omninumpy-0.1.65.dist-info/WHEEL
omninumpy-0.1.65.dist-info/top_level.txt
omninumpy-0.1.65.dist-info/RECORD
