Metadata-Version: 2.4
Name: omninumpy
Version: 0.1.65
Summary: Compatibility layer for NumPy 2.x with GPU acceleration support
Home-page: https://github.com/omninumpy/omninumpy
Author: OmniNumPy Contributors
Author-email: Ryan Walters <ryanwalters@gmail.com>
License: BSD-3-Clause
Project-URL: Homepage, https://github.com/ryanswalters/OmniNumpy
Project-URL: Repository, https://github.com/ryanswalters/OmniNumpy
Project-URL: Issues, https://github.com/ryanswalters/OmniNumpy/issues
Classifier: Development Status :: 3 - Alpha
Classifier: Intended Audience :: Developers
Classifier: Intended Audience :: Science/Research
Classifier: License :: OSI Approved :: BSD License
Classifier: Programming Language :: Python :: 3
Classifier: Programming Language :: Python :: 3.8
Classifier: Programming Language :: Python :: 3.9
Classifier: Programming Language :: Python :: 3.10
Classifier: Programming Language :: Python :: 3.11
Classifier: Programming Language :: Python :: 3.12
Classifier: Topic :: Scientific/Engineering
Requires-Python: >=3.7
License-File: LICENSE
Requires-Dist: numpy>=1.20.0
Provides-Extra: gpu
Requires-Dist: cupy-cuda12x; platform_machine == "x86_64" and extra == "gpu"
Provides-Extra: jax
Requires-Dist: jax[cpu]; extra == "jax"
Requires-Dist: jaxlib; extra == "jax"
Provides-Extra: all
Requires-Dist: cupy-cuda12x; platform_machine == "x86_64" and extra == "all"
Requires-Dist: jax[cpu]; extra == "all"
Requires-Dist: jaxlib; extra == "all"
Provides-Extra: dev
Requires-Dist: pytest>=6.0; extra == "dev"
Requires-Dist: pytest-cov; extra == "dev"
Requires-Dist: black; extra == "dev"
Requires-Dist: flake8; extra == "dev"
Requires-Dist: mypy; extra == "dev"
Dynamic: author
Dynamic: home-page
Dynamic: license-file
Dynamic: requires-python
